CHANGELOG.md
README.md
mitol/__init__.py
mitol/olposthog/__init__.py
mitol/olposthog/apps.py
mitol/olposthog/features.py
mitol/olposthog/settings/__init__.py
mitol/olposthog/settings/olposthog.py
mitol_django_olposthog-2025.8.1.dist-info/METADATA
mitol_django_olposthog-2025.8.1.dist-info/WHEEL
mitol_django_olposthog-2025.8.1.dist-info/RECORD
