Metadata-Version: 2.4
Name: mitol-django-olposthog
Version: 2025.8.1
Summary: MIT Open Learning django app extensions for Posthog.
License-Expression: BSD-3-Clause
Requires-Python: >=3.10
Requires-Dist: django-stubs>=1.13.1
Requires-Dist: django>=3.0
Requires-Dist: mitol-django-common
Requires-Dist: posthog<7,>=6.3.1
